<common>

    <base href="http://www.jdhp.org/" />
    <!-- <base href="http://www.jdhp.org/" /> -->
    <!-- <base href="https://www.lri.fr/~decock/" /> -->
    <!-- <base href="./" /> -->

    <thumbnail_base href="medias/thumbnails/" />
    <img_base href="http://download.tuxfamily.org/jdhp/image/" />
    <video_base href="http://download.tuxfamily.org/jdhp/video/" />
    <pdf_base href="http://download.tuxfamily.org/jdhp/pdf/" />
    <archive_base href="http://download.tuxfamily.org/jdhp/tarball/" />
    <debian_package_base href="http://download.tuxfamily.org/jdhp/debian/" />

</common>
