<?xml version="1.0" encoding="UTF-8" standalone="no"?>
<!--
    Semantic JDHP
    Copyright (c) 2011 Jérémie DECOCK (http://www.jdhp.org)
-->
<page>
    <name lang="fr">Tutoriels</name>
    <name lang="en">Tutorials</name>

    <keywords lang="fr">jdhp, tutoriel, vim, orthographe</keywords>
    <keywords lang="en">jdhp, tutorial</keywords>

    <desc lang="fr">
        Tutoriels informatiques.
    </desc>
    <desc lang="en">
        There are no tutorial available in english language for now.
    </desc>

    <!-- ############################################################ -->

    <group id="vim">
        <label lang="fr">VIM</label>

        <item id="vim_spell" license="cc-by-sa">
            <label lang="fr">
                Introduction à la correction orthographique avec Vim
            </label>
            
			<desc lang="fr">
                Ce document explique comment installer et utiliser la correction
                orthographique pour la langue française dans l'éditeur Vim.
                [...]
			</desc>
	
			<pdf filename="tutoriel_vim_spellfr.pdf">
                <label lang="fr">PDF</label>
			</pdf>

			<git_repository url="git://git.tuxfamily.org/gitroot/jdhp/articles.git"
                            weburl="http://git.tuxfamily.org/jdhp/articles/" />

			<link url="http://www.jdhp.org/articles/tutoriel_vim_spellfr.html">
                <label lang="fr">Lire la suite</label>
			</link>
        </item>
    </group>
</page>
